application/__init__.py
application/file.py
application/page.py
application/rule_engine.py
application/user.py
chunking_parser/__init__.py
chunking_parser/file_service.py
chunking_parser/parser_service.py
chunking_parser/request_model.py
chunking_parser/dto/__init__.py
chunking_parser/dto/file.py
chunking_parser/strategy/__init__.py
chunking_parser/strategy/strategy_abs.py
chunking_parser/strategy/strategy_factory.py
chunking_parser/strategy/strategy_implementation.py
chunking_parser-0.2.0.dist-info/METADATA
chunking_parser-0.2.0.dist-info/WHEEL
chunking_parser-0.2.0.dist-info/top_level.txt
chunking_parser-0.2.0.dist-info/RECORD
